calimero_client_py_bindings-0.2.2.dist-info/METADATA
calimero_client_py_bindings-0.2.2.dist-info/WHEEL
calimero_client_py_bindings/__init__.py
calimero_client_py_bindings/__pycache__/__init__.cpython-313.pyc
calimero_client_py_bindings/calimero_client_py_bindings.cpython-313-darwin.so
calimero_client_py_bindings/cli.py
calimero_client_py_bindings-0.2.2.dist-info/RECORD
