Metadata-Version: 2.4
Name: calimero-client-py-bindings
Version: 0.2.2
Summary: Python bindings for Calimero client library
Author-email: Calimero Network <support@calimero.network>
Requires-Python: >=3.9
